odoo/addons/crm_industry/README.rst
odoo/addons/crm_industry/__init__.py
odoo/addons/crm_industry/__manifest__.py
odoo/addons/crm_industry/i18n/bg.po
odoo/addons/crm_industry/i18n/crm_industry.pot
odoo/addons/crm_industry/i18n/crm_sector.pot
odoo/addons/crm_industry/i18n/de.po
odoo/addons/crm_industry/i18n/es.po
odoo/addons/crm_industry/i18n/fr.po
odoo/addons/crm_industry/i18n/hr.po
odoo/addons/crm_industry/i18n/it.po
odoo/addons/crm_industry/i18n/nb.po
odoo/addons/crm_industry/i18n/nl_NL.po
odoo/addons/crm_industry/i18n/pt_BR.po
odoo/addons/crm_industry/i18n/sk.po
odoo/addons/crm_industry/i18n/sl.po
odoo/addons/crm_industry/i18n/sv.po
odoo/addons/crm_industry/i18n/tr.po
odoo/addons/crm_industry/i18n/tr_TR.po
odoo/addons/crm_industry/i18n/zh_CN.po
odoo/addons/crm_industry/migrations/11.0.1.0.0/openupgrade_analysis.txt
odoo/addons/crm_industry/migrations/11.0.1.0.0/openupgrade_analysis_work.txt
odoo/addons/crm_industry/migrations/11.0.1.0.0/pre-migration.py
odoo/addons/crm_industry/models/__init__.py
odoo/addons/crm_industry/models/crm_lead.py
odoo/addons/crm_industry/readme/CONTRIBUTORS.rst
odoo/addons/crm_industry/readme/DESCRIPTION.rst
odoo/addons/crm_industry/static/description/icon.png
odoo/addons/crm_industry/static/description/index.html
odoo/addons/crm_industry/tests/__init__.py
odoo/addons/crm_industry/tests/test_crm_lead.py
odoo/addons/crm_industry/views/crm_lead_view.xml
odoo11_addon_crm_industry-11.0.1.0.0.99.dev10.dist-info/METADATA
odoo11_addon_crm_industry-11.0.1.0.0.99.dev10.dist-info/WHEEL
odoo11_addon_crm_industry-11.0.1.0.0.99.dev10.dist-info/top_level.txt
odoo11_addon_crm_industry-11.0.1.0.0.99.dev10.dist-info/RECORD
